LICENSE
README.md
make_agent/__init__.py
make_agent-0.0.0.dist-info/LICENSE
make_agent-0.0.0.dist-info/METADATA
make_agent-0.0.0.dist-info/WHEEL
make_agent-0.0.0.dist-info/RECORD
