Metadata-Version: 2.1
Name: make_agent
Version: 0.0.0
Summary: 
Home-page: https://github.com/sradc/make_agents
License: Apache-2.0
Author: sradc
Author-email: sidneyradcliffe@sky.com
Requires-Python: >=3.9
Classifier: License :: OSI Approved :: Apache Software License
Classifier: Programming Language :: Python :: 3
Classifier: Programming Language :: Python :: 3.9
Classifier: Programming Language :: Python :: 3.10
Classifier: Programming Language :: Python :: 3.11
Requires-Dist: importlib-metadata (>=6.8.0,<7.0.0)
Project-URL: Repository, https://github.com/sradc/make_agents
